specado-0.2.2.dist-info/METADATA
specado-0.2.2.dist-info/WHEEL
specado/__init__.py
specado/_native.abi3.so
specado/compat/__init__.py
specado/compat/openai.py
specado/providers/anthropic/README.md
specado/providers/anthropic/_base.yaml
specado/providers/anthropic/claude-3.5/sonnet.yaml
specado/providers/anthropic/claude-3/opus.yaml
specado/providers/anthropic/claude-4.5/sonnet.yaml
specado/providers/anthropic/claude-4/opus.yaml
specado/providers/openai/README.md
specado/providers/openai/_base-chat-completions.yaml
specado/providers/openai/_base-responses.yaml
specado/providers/openai/gpt-3.5/chat.yaml
specado/providers/openai/gpt-4/o.yaml
specado/providers/openai/gpt-4/turbo.yaml
specado/providers/openai/gpt-5/base.yaml
specado/providers/openai/gpt-5/chat.yaml
specado-0.2.2.dist-info/RECORD
