Metadata-Version: 2.4
Name: specado
Version: 0.2.2
Classifier: Programming Language :: Rust
Classifier: Programming Language :: Python :: 3.9
Classifier: Programming Language :: Python :: 3.10
Classifier: Programming Language :: Python :: 3.11
Classifier: Programming Language :: Python :: 3.12
Requires-Dist: pyyaml>=6.0,<7.0
Summary: Spec-driven LLM abstraction library
License: Apache-2.0
Requires-Python: >=3.9
